modelbatch/__init__.py
modelbatch/callbacks.py
modelbatch/core.py
modelbatch/data.py
modelbatch/huggingface_integration.py
modelbatch/logger.py
modelbatch/optimizer.py
modelbatch/optuna_integration.py
modelbatch/utils.py
modelbatch-0.1.0.dist-info/licenses/LICENSE
modelbatch-0.1.0.dist-info/METADATA
modelbatch-0.1.0.dist-info/WHEEL
modelbatch-0.1.0.dist-info/top_level.txt
modelbatch-0.1.0.dist-info/RECORD
